sparkmonitor/__init__.py
sparkmonitor/_version.py
sparkmonitor/kernelextension.py
sparkmonitor/listener_2.12.jar
sparkmonitor/listener_2.13.jar
sparkmonitor/nbextension/301.js
sparkmonitor/nbextension/301.js.LICENSE.txt
sparkmonitor/nbextension/301.js.map
sparkmonitor/nbextension/608.js
sparkmonitor/nbextension/608.js.LICENSE.txt
sparkmonitor/nbextension/608.js.map
sparkmonitor/nbextension/extension.js
sparkmonitor/nbextension/extension.js.LICENSE.txt
sparkmonitor/nbextension/extension.js.map
sparkmonitor/nbextension/sparkmonitortaskchart.js
sparkmonitor/nbextension/sparkmonitortaskchart.js.map
sparkmonitor/nbextension/sparkmonitortimeline.js
sparkmonitor/nbextension/sparkmonitortimeline.js.map
sparkmonitor-3.1.0.data/data/share/jupyter/labextensions/sparkmonitor/package.json
sparkmonitor-3.1.0.data/data/share/jupyter/labextensions/sparkmonitor/static/117.7c947fe9e57645837d1a.js
sparkmonitor-3.1.0.data/data/share/jupyter/labextensions/sparkmonitor/static/130.2531941428987e00556b.js
sparkmonitor-3.1.0.data/data/share/jupyter/labextensions/sparkmonitor/static/130.2531941428987e00556b.js.LICENSE.txt
sparkmonitor-3.1.0.data/data/share/jupyter/labextensions/sparkmonitor/static/192.f0053d42a414930376c3.js
sparkmonitor-3.1.0.data/data/share/jupyter/labextensions/sparkmonitor/static/262.ca4dd342fb3c0a038e99.js
sparkmonitor-3.1.0.data/data/share/jupyter/labextensions/sparkmonitor/static/262.ca4dd342fb3c0a038e99.js.LICENSE.txt
sparkmonitor-3.1.0.data/data/share/jupyter/labextensions/sparkmonitor/static/342.8bddc4251b40d7c5e40f.js
sparkmonitor-3.1.0.data/data/share/jupyter/labextensions/sparkmonitor/static/68.aa4907fc6d2dcff8a014.js
sparkmonitor-3.1.0.data/data/share/jupyter/labextensions/sparkmonitor/static/68.aa4907fc6d2dcff8a014.js.LICENSE.txt
sparkmonitor-3.1.0.data/data/share/jupyter/labextensions/sparkmonitor/static/717.4132bd98f81cbc55af6e.js
sparkmonitor-3.1.0.data/data/share/jupyter/labextensions/sparkmonitor/static/831.1dde83e963981bf02843.js
sparkmonitor-3.1.0.dist-info/METADATA
sparkmonitor-3.1.0.dist-info/WHEEL
sparkmonitor-3.1.0.dist-info/licenses/LICENSE
sparkmonitor-3.1.0.dist-info/RECORD
