Metadata-Version: 2.4
Name: sparkmonitor
Version: 3.1.0
Dynamic: Keywords
Summary: Jupyter Notebook & Lab extension to monitor Apache Spark jobs from a notebook
Project-URL: Homepage, https://github.com/swan-cern/sparkmonitor
Project-URL: Bug Tracker, https://github.com/swan-cern/sparkmonitor/issues
Project-URL: Repository, https://github.com/swan-cern/sparkmonitor.git
Author-email: Krishnan R <krishnanr1997@gmail.com>
License:                                  Apache License
License-File: LICENSE
Classifier: Framework :: Jupyter
Classifier: Framework :: Jupyter :: JupyterLab
Classifier: Framework :: Jupyter :: JupyterLab :: 4
Classifier: Framework :: Jupyter :: JupyterLab :: Extensions
Classifier: Framework :: Jupyter :: JupyterLab :: Extensions :: Prebuilt
Classifier: License :: OSI Approved :: Apache Software License
Classifier: Programming Language :: Python
Classifier: Programming Language :: Python :: 3
Classifier: Programming Language :: Python :: 3.8
Classifier: Programming Language :: Python :: 3.9
Classifier: Programming Language :: Python :: 3.10
Classifier: Programming Language :: Python :: 3.11
Classifier: Programming Language :: Python :: 3.12
Requires-Python: >=3.8
